src/cpu/rf.sv
module rf(
    input logic clk,
    input logic rw,
    input logic [4:0] rs1,
    input logic [4:0] rs2,
    input logic [4:0] rd,
    input logic [31:0] wd,
    output logic [31:0] out_rs1,
    output logic [31:0] out_rs2
);

logic [31:0] regs [32];

always_comb begin
    out_rs1 = rs1 != 0 ? regs[rs1] : 32'b0; 
    out_rs2 = rs2 != 0 ? regs[rs2] : 32'b0; 

end

always_ff @(posedge clk) begin
    if (rw && rd != 5'd0)
        regs[rd] <= wd;

end
endmodule

tb/tb_rf.sv
module tb_rf;
    logic clk = 0;
    logic rw;
    logic [4:0] rs1;
    logic [4:0] rs2;
    logic [4:0] rd;
    logic [31:0] wd;
    logic [31:0] out_rs1;
    logic [31:0] out_rs2;


    rf dut (
        .clk (clk),
        .rw (rw),
        .rs1 (rs1),
        .rs2 (rs2),
        .rd (rd),
        .wd (wd),
        .out_rs1 (out_rs1),
        .out_rs2 (out_rs2)
    );

    always #10  clk = ~clk;

    initial begin
        $dumpfile("sim/rf.vcd");
        $dumpvars(0, tb_rf);
        
            // TEST 1: Write then read

            rw = 1'b1; rd = 5'b1; wd = 32'b10101; @(posedge clk); #1; // Write
            rw = 1'b0; rs1 = 5'b1; #1; // Read
            assert(out_rs1 == 32'b10101) else $error ("WRITE/READ failed (TEST 1)");

            // TEST 2: Write with rw = 0

            rw = 1'b1; rd = 5'b1; wd = 32'b1; @(posedge clk); #1; // Write with rw = 1
            rw = 1'b0; rd = 5'b1; wd = 32'b10; @(posedge clk); #1; // Write with rw = 0
            rs1 = 5'b1; #1; // Read
            assert(out_rs1 == 32'b1) else $error ("Write with rw = 0 failed (TEST 2)");

            // TEST 3: Write twice, and then read
            
            rw = 1'b1; rd = 5'b1; wd = 32'b1; @(posedge clk); #1; // Write once
            rw = 1'b1; rd = 5'b1; wd = 32'b10; @(posedge clk); #1; // Write twice
            rs1 = 5'b1; #1; // Read
            assert(out_rs1 == 32'b10) else $error ("Write twice failed (TEST 3)");

            // TEST 4: x0 stays 0
            rw = 1'b1; rd = 5'b0; wd = 32'b1; @(posedge clk); #1; // Write to R0
            rs1 = 5'b0; #1; // Read
            assert(out_rs1 == 32'b0) else $error ("immutable x0 failed (TEST 4)");


            
            
            $display("All tests passed!");
            $finish;
        end
endmodule

sim/rf.vcd
$date
	Wed Aug 12 16:32:09 2026
$end
$version
	Icarus Verilog
$end
$timescale
	1s
$end
$scope module tb_rf $end
$var wire 32 ! out_rs2 [31:0] $end
$var wire 32 " out_rs1 [31:0] $end
$var reg 1 # clk $end
$var reg 5 $ rd [4:0] $end
$var reg 5 % rs1 [4:0] $end
$var reg 5 & rs2 [4:0] $end
$var reg 1 ' rw $end
$var reg 32 ( wd [31:0] $end
$scope module dut $end
$var wire 1 # clk $end
$var wire 5 ) rd [4:0] $end
$var wire 5 * rs1 [4:0] $end
$var wire 5 + rs2 [4:0] $end
$var wire 1 ' rw $end
$var wire 32 , wd [31:0] $end
$var reg 32 - out_rs1 [31:0] $end
$var reg 32 . out_rs2 [31:0] $end
$upscope $end
$upscope $end
$enddefinitions $end
$comment Show the parameter values. $end
$dumpall
$end
#0
$dumpvars
bx .
bx -
b10101 ,
bx +
bx *
b1 )
b10101 (
1'
bx &
bx %
b1 $
0#
bx "
bx !
$end
#10
1#
#11
b10101 "
b10101 -
b1 %
b1 *
0'
#12
b1 (
b1 ,
1'
#20
0#
#30
b1 "
b1 -
1#
#31
b10 (
b10 ,
0'
#40
0#
#50
1#
#52
b1 (
b1 ,
1'
#60
0#
#70
1#
#71
b10 (
b10 ,
#80
0#
#90
b10 "
b10 -
1#
#92
b1 (
b1 ,
b0 $
b0 )
#100
0#
#110
1#
#111
b0 "
b0 -
b0 %
b0 *
